{
  "checked_candidate_file_ref": "sha256:7702152bcded5d335a18508b3d8d077e7eaf9e7bdb95cfa739bb89246d0f5de4",
  "forbidden_axiom_status": "clean",
  "lean_artifact_ref": "C:\\Users\\bakat\\work\\AI_math_research\\runs\\geometry_full2d_v0_4_2\\proof_artifact_batch\\full2d-curated-0427\\worker\\full2d_release_proof_artifact_batch\\full2d-curated-0427\\full2d_curated_0427.lean",
  "lean_status": "passed",
  "proof_artifact_ref": "C:\\Users\\bakat\\work\\AI_math_research\\runs\\geometry_full2d_v0_4_2\\proof_artifact_batch\\full2d-curated-0427\\worker\\full2d_release_proof_artifact_batch\\full2d-curated-0427\\full2d_curated_0427.lean",
  "proof_region_guard_status": "passed",
  "proof_use_provenance_status": "passed",
  "proof_use_status": "final_theorem",
  "protected_statement_hash_source": "source_problem",
  "protected_theorem_hash_unchanged": true,
  "report_id": "FinalVerifyGateFull2D:d8830b5aec1e36e0faf83538b6e220a65104602656d2f465bb2ebf6d5baadac9",
  "schema_version": "1.0.0",
  "solver_backed_proof_status": "passed",
  "sorry_status": "clean",
  "target_obligation_id": "full2d-obligation:full2d-curated-0427",
  "theorem_statement_hash": "sha256:b8c67adb0aa3637c8422e241cddec163556a3e35f7197ed2bd9d9be82e7b2a57"
}
