{
  "checked_candidate_file_ref": "sha256:f26388ec25aacebdba9b9808be45c24dabf202bdb5aed94140eba89c1fefc07d",
  "forbidden_axiom_status": "clean",
  "lean_artifact_ref": "C:\\Users\\bakat\\work\\AI_math_research\\runs\\geometry_full2d_v0_4_2\\proof_artifact_batch\\full2d-curated-2721\\worker\\full2d_release_proof_artifact_batch\\full2d-curated-2721\\full2d_curated_2721.lean",
  "lean_status": "passed",
  "proof_artifact_ref": "C:\\Users\\bakat\\work\\AI_math_research\\runs\\geometry_full2d_v0_4_2\\proof_artifact_batch\\full2d-curated-2721\\worker\\full2d_release_proof_artifact_batch\\full2d-curated-2721\\full2d_curated_2721.lean",
  "proof_region_guard_status": "passed",
  "proof_use_provenance_status": "passed",
  "proof_use_status": "final_theorem",
  "protected_statement_hash_source": "source_problem",
  "protected_theorem_hash_unchanged": true,
  "report_id": "FinalVerifyGateFull2D:f0ec6e7783191213de83541e5898668312f9afb90ee0f742bdc688644c7f2935",
  "schema_version": "1.0.0",
  "solver_backed_proof_status": "passed",
  "sorry_status": "clean",
  "target_obligation_id": "full2d-obligation:full2d-curated-2721",
  "theorem_statement_hash": "sha256:b1bce798e3adebf212cd786a3178369653fad8addabcc4933644387127bb28a3"
}
