{
  "checked_candidate_file_ref": "sha256:e2209ff3722c6f7344123443769dd28da98f3e65be805f0d9da3c638cb5861fb",
  "forbidden_axiom_status": "clean",
  "lean_artifact_ref": "C:\\Users\\bakat\\work\\AI_math_research\\runs\\geometry_full2d_v0_4_2\\proof_artifact_batch\\full2d-positive-2057\\worker\\full2d_release_proof_artifact_batch\\full2d-positive-2057\\full2d_synth_2057.lean",
  "lean_status": "passed",
  "proof_artifact_ref": "C:\\Users\\bakat\\work\\AI_math_research\\runs\\geometry_full2d_v0_4_2\\proof_artifact_batch\\full2d-positive-2057\\worker\\full2d_release_proof_artifact_batch\\full2d-positive-2057\\full2d_synth_2057.lean",
  "proof_region_guard_status": "passed",
  "proof_use_provenance_status": "passed",
  "proof_use_status": "final_theorem",
  "protected_statement_hash_source": "source_problem",
  "protected_theorem_hash_unchanged": true,
  "report_id": "FinalVerifyGateFull2D:f550baae94196185b93d729fb95284d9b714384734c2ac64adfbe4432a460a6c",
  "schema_version": "1.0.0",
  "solver_backed_proof_status": "passed",
  "sorry_status": "clean",
  "target_obligation_id": "full2d-obligation:full2d-positive-2057",
  "theorem_statement_hash": "sha256:89b02679bec4d54a3e5f360d35868c5ed39960270240ffe073bf4ea40913eec8"
}
