{
  "checked_candidate_file_ref": "sha256:8c0947895bef3c49ed3c5feb449010982468ac9aec256e5d5e4a7bcde754416e",
  "forbidden_axiom_status": "clean",
  "lean_artifact_ref": "C:\\Users\\bakat\\work\\AI_math_research\\runs\\geometry_full2d_v0_4_2\\proof_artifact_batch\\full2d-positive-2130\\worker\\full2d_release_proof_artifact_batch\\full2d-positive-2130\\full2d_synth_2130.lean",
  "lean_status": "passed",
  "proof_artifact_ref": "C:\\Users\\bakat\\work\\AI_math_research\\runs\\geometry_full2d_v0_4_2\\proof_artifact_batch\\full2d-positive-2130\\worker\\full2d_release_proof_artifact_batch\\full2d-positive-2130\\full2d_synth_2130.lean",
  "proof_region_guard_status": "passed",
  "proof_use_provenance_status": "passed",
  "proof_use_status": "final_theorem",
  "protected_statement_hash_source": "source_problem",
  "protected_theorem_hash_unchanged": true,
  "report_id": "FinalVerifyGateFull2D:6571678c0defd49bbcdda0169e01d3bafb31b536dc4df6cd42762b84927d1096",
  "schema_version": "1.0.0",
  "solver_backed_proof_status": "passed",
  "sorry_status": "clean",
  "target_obligation_id": "full2d-obligation:full2d-positive-2130",
  "theorem_statement_hash": "sha256:2a410f56a5368191b1f964d89e05032bf50a9fa7cbf3d184bad6c850d4c1f1fe"
}
