{
  "checked_candidate_file_ref": "sha256:57db37a65e75436a296d735fd46a143e008bb68152cd4afac1aecdee5bec7f3b",
  "forbidden_axiom_status": "clean",
  "lean_artifact_ref": "C:\\Users\\bakat\\work\\AI_math_research\\runs\\geometry_full2d_v0_4_2\\proof_artifact_batch\\full2d-curated-1579\\worker\\full2d_release_proof_artifact_batch\\full2d-curated-1579\\full2d_curated_1579.lean",
  "lean_status": "passed",
  "proof_artifact_ref": "C:\\Users\\bakat\\work\\AI_math_research\\runs\\geometry_full2d_v0_4_2\\proof_artifact_batch\\full2d-curated-1579\\worker\\full2d_release_proof_artifact_batch\\full2d-curated-1579\\full2d_curated_1579.lean",
  "proof_region_guard_status": "passed",
  "proof_use_provenance_status": "passed",
  "proof_use_status": "final_theorem",
  "protected_statement_hash_source": "source_problem",
  "protected_theorem_hash_unchanged": true,
  "report_id": "FinalVerifyGateFull2D:018cbcfaa4ca36ec0a8686bfa0c9d7d114e37a4c27879504bf784c7b4554e3c0",
  "schema_version": "1.0.0",
  "solver_backed_proof_status": "passed",
  "sorry_status": "clean",
  "target_obligation_id": "full2d-obligation:full2d-curated-1579",
  "theorem_statement_hash": "sha256:cf4b1cae71157c2ee7e523756fa674b1d4376fc5c1aff262caa183a723baea8a"
}
