{
  "checked_candidate_file_ref": "sha256:e729af34348b97c71ea8b27d0f2e4ecb8b5e26503b3d3a8309fa09cf0e84646a",
  "forbidden_axiom_status": "clean",
  "lean_artifact_ref": "C:\\Users\\bakat\\work\\AI_math_research\\runs\\geometry_full2d_v0_4_2\\proof_artifact_batch\\full2d-curated-2895\\worker\\full2d_release_proof_artifact_batch\\full2d-curated-2895\\full2d_curated_2895.lean",
  "lean_status": "passed",
  "proof_artifact_ref": "C:\\Users\\bakat\\work\\AI_math_research\\runs\\geometry_full2d_v0_4_2\\proof_artifact_batch\\full2d-curated-2895\\worker\\full2d_release_proof_artifact_batch\\full2d-curated-2895\\full2d_curated_2895.lean",
  "proof_region_guard_status": "passed",
  "proof_use_provenance_status": "passed",
  "proof_use_status": "final_theorem",
  "protected_statement_hash_source": "source_problem",
  "protected_theorem_hash_unchanged": true,
  "report_id": "FinalVerifyGateFull2D:44e274610aa3c629fe0671f5d84c015dcbc7f470b9d9a6b497afde7bde8a12d6",
  "schema_version": "1.0.0",
  "solver_backed_proof_status": "passed",
  "sorry_status": "clean",
  "target_obligation_id": "full2d-obligation:full2d-curated-2895",
  "theorem_statement_hash": "sha256:61150f26e0bc2ea3b1db4f6c60ee42ae8580d781272955a426f9fa0e4b63a459"
}
