{
  "checked_candidate_file_ref": "sha256:15087139a3271f43c09ec167acd39f9e037c3e1af227bd4141724867a4b37fc2",
  "forbidden_axiom_status": "clean",
  "lean_artifact_ref": "C:\\Users\\bakat\\work\\AI_math_research\\runs\\geometry_full2d_v0_4_2\\proof_artifact_batch\\full2d-curated-0059\\worker\\full2d_release_proof_artifact_batch\\full2d-curated-0059\\full2d_curated_0059.lean",
  "lean_status": "passed",
  "proof_artifact_ref": "C:\\Users\\bakat\\work\\AI_math_research\\runs\\geometry_full2d_v0_4_2\\proof_artifact_batch\\full2d-curated-0059\\worker\\full2d_release_proof_artifact_batch\\full2d-curated-0059\\full2d_curated_0059.lean",
  "proof_region_guard_status": "passed",
  "proof_use_provenance_status": "passed",
  "proof_use_status": "final_theorem",
  "protected_statement_hash_source": "source_problem",
  "protected_theorem_hash_unchanged": true,
  "report_id": "FinalVerifyGateFull2D:c08e9ef8f58299dfabc87296acd263bbdf4d4c5d6147c1f2b6220502fb7db979",
  "schema_version": "1.0.0",
  "solver_backed_proof_status": "passed",
  "sorry_status": "clean",
  "target_obligation_id": "full2d-obligation:full2d-curated-0059",
  "theorem_statement_hash": "sha256:9a3746e5436facd322a0f4aa8c0fd5ae22f39f5dc08598b83c288a2216a9980c"
}
