{
  "checked_candidate_file_ref": "sha256:237539bdba05f12b648d57664019452991bf0d31f18d571bb178fafa3fbe0672",
  "forbidden_axiom_status": "clean",
  "lean_artifact_ref": "C:\\Users\\bakat\\work\\AI_math_research\\runs\\geometry_full2d_v0_4_2\\proof_artifact_batch\\full2d-curated-1350\\worker\\full2d_release_proof_artifact_batch\\full2d-curated-1350\\full2d_curated_1350.lean",
  "lean_status": "passed",
  "proof_artifact_ref": "C:\\Users\\bakat\\work\\AI_math_research\\runs\\geometry_full2d_v0_4_2\\proof_artifact_batch\\full2d-curated-1350\\worker\\full2d_release_proof_artifact_batch\\full2d-curated-1350\\full2d_curated_1350.lean",
  "proof_region_guard_status": "passed",
  "proof_use_provenance_status": "passed",
  "proof_use_status": "final_theorem",
  "protected_statement_hash_source": "source_problem",
  "protected_theorem_hash_unchanged": true,
  "report_id": "FinalVerifyGateFull2D:56a3960bb738f1bb2215d74482311503c9ab11e8eea19b36d9e708d2fc8fa815",
  "schema_version": "1.0.0",
  "solver_backed_proof_status": "passed",
  "sorry_status": "clean",
  "target_obligation_id": "full2d-obligation:full2d-curated-1350",
  "theorem_statement_hash": "sha256:693d46a7943955349923f5a1cab2ba2352fa326c28285f9f6ab188e579247395"
}
