{
  "checked_candidate_file_ref": "sha256:ef5d099032066c1f1b9a3a46f05b555b3576bda060efc10f304db9d1e550959f",
  "forbidden_axiom_status": "clean",
  "lean_artifact_ref": "C:\\Users\\bakat\\work\\AI_math_research\\runs\\geometry_full2d_v0_4_2\\proof_artifact_batch\\full2d-positive-2229\\worker\\full2d_release_proof_artifact_batch\\full2d-positive-2229\\full2d_synth_2229.lean",
  "lean_status": "passed",
  "proof_artifact_ref": "C:\\Users\\bakat\\work\\AI_math_research\\runs\\geometry_full2d_v0_4_2\\proof_artifact_batch\\full2d-positive-2229\\worker\\full2d_release_proof_artifact_batch\\full2d-positive-2229\\full2d_synth_2229.lean",
  "proof_region_guard_status": "passed",
  "proof_use_provenance_status": "passed",
  "proof_use_status": "final_theorem",
  "protected_statement_hash_source": "source_problem",
  "protected_theorem_hash_unchanged": true,
  "report_id": "FinalVerifyGateFull2D:a874183684c3c121f1b6d013c0ab56e0ac10859b9c2c481bcc3a2bde10c634e3",
  "schema_version": "1.0.0",
  "solver_backed_proof_status": "passed",
  "sorry_status": "clean",
  "target_obligation_id": "full2d-obligation:full2d-positive-2229",
  "theorem_statement_hash": "sha256:5ae75b9534bf5c125997871dec8abaef80efab4818369cd4b1e3bfcd6e1aaeed"
}
