{
  "checked_candidate_file_ref": "sha256:4f81c2fab74c60f553ee8e0234512f5ed9a9776e9062695506aeea981cf40312",
  "forbidden_axiom_status": "clean",
  "lean_artifact_ref": "C:\\Users\\bakat\\work\\AI_math_research\\runs\\geometry_full2d_v0_4_2\\proof_artifact_batch\\full2d-positive-1285\\worker\\full2d_release_proof_artifact_batch\\full2d-positive-1285\\full2d_synth_1285.lean",
  "lean_status": "passed",
  "proof_artifact_ref": "C:\\Users\\bakat\\work\\AI_math_research\\runs\\geometry_full2d_v0_4_2\\proof_artifact_batch\\full2d-positive-1285\\worker\\full2d_release_proof_artifact_batch\\full2d-positive-1285\\full2d_synth_1285.lean",
  "proof_region_guard_status": "passed",
  "proof_use_provenance_status": "passed",
  "proof_use_status": "final_theorem",
  "protected_statement_hash_source": "source_problem",
  "protected_theorem_hash_unchanged": true,
  "report_id": "FinalVerifyGateFull2D:e83dd8402c9e471bfc497b0803f7057b28c8662e6dce7c7ae49b12c4fbf68cfa",
  "schema_version": "1.0.0",
  "solver_backed_proof_status": "passed",
  "sorry_status": "clean",
  "target_obligation_id": "full2d-obligation:full2d-positive-1285",
  "theorem_statement_hash": "sha256:4675e502ece2fe58e898f2d5c333c312c197c623180c576aa23af845d01b4785"
}
