{
  "checked_candidate_file_ref": "sha256:36a7c84038c077ec2fd8ef5eab283813f4adf7582f2724c0030976bd4d910ffd",
  "forbidden_axiom_status": "clean",
  "lean_artifact_ref": "C:\\Users\\bakat\\work\\AI_math_research\\runs\\geometry_full2d_v0_4_2\\proof_artifact_batch\\full2d-positive-0144\\worker\\full2d_release_proof_artifact_batch\\full2d-positive-0144\\full2d_synth_0144.lean",
  "lean_status": "passed",
  "proof_artifact_ref": "C:\\Users\\bakat\\work\\AI_math_research\\runs\\geometry_full2d_v0_4_2\\proof_artifact_batch\\full2d-positive-0144\\worker\\full2d_release_proof_artifact_batch\\full2d-positive-0144\\full2d_synth_0144.lean",
  "proof_region_guard_status": "passed",
  "proof_use_provenance_status": "passed",
  "proof_use_status": "final_theorem",
  "protected_statement_hash_source": "source_problem",
  "protected_theorem_hash_unchanged": true,
  "report_id": "FinalVerifyGateFull2D:dbd94b72779f173a7ac3cc15357fe202812d8af2e7fe4a12902d26dcf11a41ae",
  "schema_version": "1.0.0",
  "solver_backed_proof_status": "passed",
  "sorry_status": "clean",
  "target_obligation_id": "full2d-obligation:full2d-positive-0144",
  "theorem_statement_hash": "sha256:6d95b8cd01be7374a4c7693835773cbc3eda1a092be125b854d35776eaea3034"
}
