{
  "checked_candidate_file_ref": "sha256:d91c54982b20f0868ed3f75c43b51dafd6e3ef028e8ef8a86c3c5106c9afc195",
  "forbidden_axiom_status": "clean",
  "lean_artifact_ref": "C:\\Users\\bakat\\work\\AI_math_research\\runs\\geometry_full2d_v0_4_2\\proof_artifact_batch\\full2d-positive-2701\\worker\\full2d_release_proof_artifact_batch\\full2d-positive-2701\\full2d_synth_2701.lean",
  "lean_status": "passed",
  "proof_artifact_ref": "C:\\Users\\bakat\\work\\AI_math_research\\runs\\geometry_full2d_v0_4_2\\proof_artifact_batch\\full2d-positive-2701\\worker\\full2d_release_proof_artifact_batch\\full2d-positive-2701\\full2d_synth_2701.lean",
  "proof_region_guard_status": "passed",
  "proof_use_provenance_status": "passed",
  "proof_use_status": "final_theorem",
  "protected_statement_hash_source": "source_problem",
  "protected_theorem_hash_unchanged": true,
  "report_id": "FinalVerifyGateFull2D:b4396cbc88af1703947c5f6a84622491a4311efeece76a8d7322de1c74ad1988",
  "schema_version": "1.0.0",
  "solver_backed_proof_status": "passed",
  "sorry_status": "clean",
  "target_obligation_id": "full2d-obligation:full2d-positive-2701",
  "theorem_statement_hash": "sha256:a41be0e237b32195be6eb098a03bf717244f958e56c8a7a66492d394a4a8645c"
}
