{
  "checked_candidate_file_ref": "sha256:4fe254a38b23dd26a5b67ceb00623f747597afe05264ad6db698c03028a0040b",
  "forbidden_axiom_status": "clean",
  "lean_artifact_ref": "C:\\Users\\bakat\\work\\AI_math_research\\runs\\geometry_full2d_v0_4_2\\proof_artifact_batch\\full2d-curated-0970\\worker\\full2d_release_proof_artifact_batch\\full2d-curated-0970\\full2d_curated_0970.lean",
  "lean_status": "passed",
  "proof_artifact_ref": "C:\\Users\\bakat\\work\\AI_math_research\\runs\\geometry_full2d_v0_4_2\\proof_artifact_batch\\full2d-curated-0970\\worker\\full2d_release_proof_artifact_batch\\full2d-curated-0970\\full2d_curated_0970.lean",
  "proof_region_guard_status": "passed",
  "proof_use_provenance_status": "passed",
  "proof_use_status": "final_theorem",
  "protected_statement_hash_source": "source_problem",
  "protected_theorem_hash_unchanged": true,
  "report_id": "FinalVerifyGateFull2D:a89fa9847b64f654123e606ae483180548461c51b2a97f964054fb62d8fccf89",
  "schema_version": "1.0.0",
  "solver_backed_proof_status": "passed",
  "sorry_status": "clean",
  "target_obligation_id": "full2d-obligation:full2d-curated-0970",
  "theorem_statement_hash": "sha256:afab9f75e13f6f39046b95a2bd0b033acde5783d243f5a5fd4834956837751aa"
}
