{
  "checked_candidate_file_ref": "sha256:771118f918d48d94304b656875d14076c000f74324017fea5e6854dfeaa57eff",
  "forbidden_axiom_status": "clean",
  "lean_artifact_ref": "C:\\Users\\bakat\\work\\AI_math_research\\runs\\geometry_full2d_v0_4_2\\proof_artifact_batch\\full2d-curated-2666\\worker\\full2d_release_proof_artifact_batch\\full2d-curated-2666\\full2d_curated_2666.lean",
  "lean_status": "passed",
  "proof_artifact_ref": "C:\\Users\\bakat\\work\\AI_math_research\\runs\\geometry_full2d_v0_4_2\\proof_artifact_batch\\full2d-curated-2666\\worker\\full2d_release_proof_artifact_batch\\full2d-curated-2666\\full2d_curated_2666.lean",
  "proof_region_guard_status": "passed",
  "proof_use_provenance_status": "passed",
  "proof_use_status": "final_theorem",
  "protected_statement_hash_source": "source_problem",
  "protected_theorem_hash_unchanged": true,
  "report_id": "FinalVerifyGateFull2D:42e8d9c2eddbd51f9d7448055ce7f2e76959baeb1e32f7689b24ba2955acbb3b",
  "schema_version": "1.0.0",
  "solver_backed_proof_status": "passed",
  "sorry_status": "clean",
  "target_obligation_id": "full2d-obligation:full2d-curated-2666",
  "theorem_statement_hash": "sha256:62ec0fb789e8d126eb63d4ada14de7843e73fc85549c07057e27310442fc9ded"
}
