{
  "checker_name": "check_engine_output_not_from_compiler_rules_v0_6.py",
  "engine_output_results": [
    {
      "errors": [],
      "path": "engine_outputs_v0_6/v06_bootstrap_collinear_refl__algebraic_metric_certificate.json",
      "status": "passed"
    },
    {
      "errors": [],
      "path": "engine_outputs_v0_6/v06_bootstrap_collinear_refl__construction.json",
      "status": "passed"
    },
    {
      "errors": [],
      "path": "engine_outputs_v0_6/v06_bootstrap_collinear_refl__external_solver_trace.json",
      "status": "passed"
    },
    {
      "errors": [],
      "path": "engine_outputs_v0_6/v06_bootstrap_collinear_refl__inequality.json",
      "status": "passed"
    },
    {
      "errors": [],
      "path": "engine_outputs_v0_6/v06_bootstrap_collinear_refl__lean_search_certificate.json",
      "status": "passed"
    },
    {
      "errors": [],
      "path": "engine_outputs_v0_6/v06_bootstrap_collinear_refl__order_case.json",
      "status": "passed"
    },
    {
      "errors": [],
      "path": "engine_outputs_v0_6/v06_bootstrap_collinear_refl__synthetic_trace.json",
      "status": "passed"
    },
    {
      "errors": [],
      "path": "engine_outputs_v0_6/v06_bootstrap_equal_length_symm__algebraic_metric_certificate.json",
      "status": "passed"
    },
    {
      "errors": [],
      "path": "engine_outputs_v0_6/v06_bootstrap_equal_length_symm__construction.json",
      "status": "passed"
    },
    {
      "errors": [],
      "path": "engine_outputs_v0_6/v06_bootstrap_equal_length_symm__external_solver_trace.json",
      "status": "passed"
    },
    {
      "errors": [],
      "path": "engine_outputs_v0_6/v06_bootstrap_equal_length_symm__inequality.json",
      "status": "passed"
    },
    {
      "errors": [],
      "path": "engine_outputs_v0_6/v06_bootstrap_equal_length_symm__lean_search_certificate.json",
      "status": "passed"
    },
    {
      "errors": [],
      "path": "engine_outputs_v0_6/v06_bootstrap_equal_length_symm__order_case.json",
      "status": "passed"
    },
    {
      "errors": [],
      "path": "engine_outputs_v0_6/v06_bootstrap_equal_length_symm__synthetic_trace.json",
      "status": "passed"
    },
    {
      "errors": [],
      "path": "engine_outputs_v0_6/v06_bootstrap_midpoint_collinear__algebraic_metric_certificate.json",
      "status": "passed"
    },
    {
      "errors": [],
      "path": "engine_outputs_v0_6/v06_bootstrap_midpoint_collinear__construction.json",
      "status": "passed"
    },
    {
      "errors": [],
      "path": "engine_outputs_v0_6/v06_bootstrap_midpoint_collinear__external_solver_trace.json",
      "status": "passed"
    },
    {
      "errors": [],
      "path": "engine_outputs_v0_6/v06_bootstrap_midpoint_collinear__inequality.json",
      "status": "passed"
    },
    {
      "errors": [],
      "path": "engine_outputs_v0_6/v06_bootstrap_midpoint_collinear__lean_search_certificate.json",
      "status": "passed"
    },
    {
      "errors": [],
      "path": "engine_outputs_v0_6/v06_bootstrap_midpoint_collinear__order_case.json",
      "status": "passed"
    },
    {
      "errors": [],
      "path": "engine_outputs_v0_6/v06_bootstrap_midpoint_collinear__synthetic_trace.json",
      "status": "passed"
    }
  ],
  "engine_roles_seen": [
    "algebraic_metric_certificate",
    "construction",
    "external_solver_trace",
    "inequality",
    "lean_search_certificate",
    "order_case",
    "synthetic_trace"
  ],
  "errors": [],
  "provider_run": {
    "engine_output_count": 21,
    "errors": [],
    "existing_outputs_reused": true,
    "provider_index_path": "C:\\Users\\bakat\\work\\AI_math_research\\runs\\wp05_v0_6_fresh\\provider_index_v0_6.json",
    "provider_manifest_count": 3,
    "run_dir": "C:\\Users\\bakat\\work\\AI_math_research\\runs\\wp05_v0_6_fresh",
    "schema_version": "RunProviderStageV06Report",
    "status": "passed"
  },
  "red_cases": {
    "cases": [
      {
        "checker_name": "check_red_case_suite_v0_6.py",
        "detected_K": [
          "K-007",
          "K-013"
        ],
        "errors": [],
        "evidence_ref": "sha256:990033c9dc1d765d2fdf96c3fee37e655930c97055f107b2092ca1b6c998968e",
        "expected_K": [
          "K-007",
          "K-013"
        ],
        "failure_class": "Target-fact provider",
        "fixture_name": "RedCase_TargetFactProvider",
        "fixture_path": "tests/red_cases/geometry_full2d_v0_6/manifest.json#RC-001",
        "missing_expected_K": [],
        "observed_failure": true,
        "positive_control_detected_K": [],
        "positive_control_passed": true,
        "red_case_id": "RC-001",
        "variant_results": [
          {
            "detected_K": [
              "K-007"
            ],
            "errors": [],
            "kind": "static-code",
            "variant_index": 1
          },
          {
            "detected_K": [
              "K-007",
              "K-013"
            ],
            "errors": [],
            "kind": "artifact-run",
            "variant_index": 2
          }
        ]
      },
      {
        "checker_name": "check_red_case_suite_v0_6.py",
        "detected_K": [
          "K-011"
        ],
        "errors": [],
        "evidence_ref": "sha256:685448463476f46f0db436797b51d56dbd29edb1bd7c4e9aff5899a7052e7434",
        "expected_K": [
          "K-011"
        ],
        "failure_class": "Rule-list artifact synthesis",
        "fixture_name": "RedCase_RuleListArtifactSynthesis",
        "fixture_path": "tests/red_cases/geometry_full2d_v0_6/manifest.json#RC-005",
        "missing_expected_K": [],
        "observed_failure": true,
        "positive_control_detected_K": [],
        "positive_control_passed": true,
        "red_case_id": "RC-005",
        "variant_results": [
          {
            "detected_K": [
              "K-011"
            ],
            "errors": [],
            "kind": "static-code",
            "variant_index": 1
          },
          {
            "detected_K": [
              "K-011"
            ],
            "errors": [],
            "kind": "artifact-run",
            "variant_index": 2
          }
        ]
      },
      {
        "checker_name": "check_red_case_suite_v0_6.py",
        "detected_K": [
          "K-009",
          "K-013"
        ],
        "errors": [],
        "evidence_ref": "sha256:e5a3add178e96b9c082b30890bc379d878f0baea7eaaaed8c7104e641e4ce099",
        "expected_K": [
          "K-009",
          "K-013"
        ],
        "failure_class": "Target-as-certificate",
        "fixture_name": "RedCase_TargetAsCertificate",
        "fixture_path": "tests/red_cases/geometry_full2d_v0_6/manifest.json#RC-014",
        "missing_expected_K": [],
        "observed_failure": true,
        "positive_control_detected_K": [],
        "positive_control_passed": true,
        "red_case_id": "RC-014",
        "variant_results": [
          {
            "detected_K": [
              "K-009"
            ],
            "errors": [],
            "kind": "static-code",
            "variant_index": 1
          },
          {
            "detected_K": [
              "K-009",
              "K-013"
            ],
            "errors": [],
            "kind": "artifact-run",
            "variant_index": 2
          }
        ]
      },
      {
        "checker_name": "check_red_case_suite_v0_6.py",
        "detected_K": [
          "K-010"
        ],
        "errors": [],
        "evidence_ref": "sha256:e25ac16c1e89378735a2d0700fc4b694f7feacba4d6d1911fba14a977e746d82",
        "expected_K": [
          "K-010"
        ],
        "failure_class": "Engine output contains proof text",
        "fixture_name": "EngineOutputContainsProofText",
        "fixture_path": "tests/red_cases/geometry_full2d_v0_6/manifest.json#K-010",
        "missing_expected_K": [],
        "observed_failure": true,
        "positive_control_detected_K": [],
        "positive_control_passed": true,
        "red_case_id": "K-010",
        "variant_results": [
          {
            "detected_K": [
              "K-010"
            ],
            "errors": [],
            "kind": "static-code",
            "variant_index": 1
          },
          {
            "detected_K": [
              "K-010"
            ],
            "errors": [],
            "kind": "artifact-run",
            "variant_index": 2
          }
        ]
      }
    ],
    "errors": [],
    "local_negative_results": {
      "proof_text": [
        "engine_output_contains_proof_text",
        "proof_text_in_engine_output",
        "proof_text_present",
        "selected_artifact_missing_input_context:0",
        "selected_artifact_missing_provider_algorithm:0",
        "selected_artifact_missing_role_payload:0:certificate_payload",
        "selected_artifact_missing_solver_trace:0"
      ],
      "rule_list_synthesis": [
        "engine_output_from_compiler_rules:compiler_selected_rule_list",
        "selected_artifact_from_compiler_rules:0",
        "selected_artifact_missing_input_context:0",
        "selected_artifact_missing_provider_algorithm:0",
        "selected_artifact_missing_role_payload:0:construction_payload",
        "selected_artifact_missing_solver_trace:0"
      ],
      "target_fact_provider": [
        "fact_missing_premises:0",
        "selected_artifact_contains_target_hash:0",
        "selected_artifact_is_final_target:0",
        "selected_artifact_missing_input_context:0",
        "selected_artifact_missing_premises:0",
        "selected_artifact_missing_provider_algorithm:0",
        "selected_artifact_missing_role_payload:0:trace_payload",
        "selected_artifact_missing_solver_trace:0",
        "selected_artifact_target_equivalent:0",
        "target_fact_without_derivation"
      ]
    },
    "schema_version": "EngineOutputNoCompilerRulesRedCaseReportV06",
    "status": "passed"
  },
  "run_dir": "C:\\Users\\bakat\\work\\AI_math_research\\runs\\wp05_v0_6_fresh",
  "schema_version": "CheckEngineOutputNotFromCompilerRulesV06Report",
  "status": "passed"
}
