{
  "checked_candidate_file_ref": "sha256:8b2ac45a097f2c645441c46a23bc75ef78bf45acb850351b2ec30858ebf9a7b0",
  "forbidden_axiom_status": "clean",
  "lean_artifact_ref": "C:\\Users\\bakat\\work\\AI_math_research\\runs\\geometry_full2d_v0_4_2\\proof_artifact_batch\\full2d-positive-0732\\worker\\full2d_release_proof_artifact_batch\\full2d-positive-0732\\full2d_synth_0732.lean",
  "lean_status": "passed",
  "proof_artifact_ref": "C:\\Users\\bakat\\work\\AI_math_research\\runs\\geometry_full2d_v0_4_2\\proof_artifact_batch\\full2d-positive-0732\\worker\\full2d_release_proof_artifact_batch\\full2d-positive-0732\\full2d_synth_0732.lean",
  "proof_region_guard_status": "passed",
  "proof_use_provenance_status": "passed",
  "proof_use_status": "final_theorem",
  "protected_statement_hash_source": "source_problem",
  "protected_theorem_hash_unchanged": true,
  "report_id": "FinalVerifyGateFull2D:0b648f31e7d2e2bfaea5d9bf5f30e7e4f0e8a9debb9cc2301fc51b15e7e1de43",
  "schema_version": "1.0.0",
  "solver_backed_proof_status": "passed",
  "sorry_status": "clean",
  "target_obligation_id": "full2d-obligation:full2d-positive-0732",
  "theorem_statement_hash": "sha256:a896cf79e899a80f4671e9d4a2ba188d5e1ef24b5b125a0bcb0add179bf49bee"
}
