{
  "checked_candidate_file_ref": "sha256:520ab4d9fc3fc93aa9170ba2b72048323bed4826916ab6a8962497806a83aef2",
  "forbidden_axiom_status": "clean",
  "lean_artifact_ref": "C:\\Users\\bakat\\work\\AI_math_research\\runs\\geometry_full2d_v0_4_2\\proof_artifact_batch\\full2d-positive-0819\\worker\\full2d_release_proof_artifact_batch\\full2d-positive-0819\\full2d_synth_0819.lean",
  "lean_status": "passed",
  "proof_artifact_ref": "C:\\Users\\bakat\\work\\AI_math_research\\runs\\geometry_full2d_v0_4_2\\proof_artifact_batch\\full2d-positive-0819\\worker\\full2d_release_proof_artifact_batch\\full2d-positive-0819\\full2d_synth_0819.lean",
  "proof_region_guard_status": "passed",
  "proof_use_provenance_status": "passed",
  "proof_use_status": "final_theorem",
  "protected_statement_hash_source": "source_problem",
  "protected_theorem_hash_unchanged": true,
  "report_id": "FinalVerifyGateFull2D:8514cbea28f538d3ca89ca33afd54817b7210552a42fbe8ec988c0bf67a500c7",
  "schema_version": "1.0.0",
  "solver_backed_proof_status": "passed",
  "sorry_status": "clean",
  "target_obligation_id": "full2d-obligation:full2d-positive-0819",
  "theorem_statement_hash": "sha256:cd6e73adc97eca535ff83bacdd9af36ebd0658356e01c708431b9399582a214a"
}
