{
  "checked_candidate_file_ref": "sha256:266ed6070e70482a875072eec91e3f01a98a18d280018fe66e0e3aaac892d3da",
  "forbidden_axiom_status": "clean",
  "lean_artifact_ref": "C:\\Users\\bakat\\work\\AI_math_research\\runs\\geometry_full2d_v0_4_2\\proof_artifact_batch\\full2d-curated-1056\\worker\\full2d_release_proof_artifact_batch\\full2d-curated-1056\\full2d_curated_1056.lean",
  "lean_status": "passed",
  "proof_artifact_ref": "C:\\Users\\bakat\\work\\AI_math_research\\runs\\geometry_full2d_v0_4_2\\proof_artifact_batch\\full2d-curated-1056\\worker\\full2d_release_proof_artifact_batch\\full2d-curated-1056\\full2d_curated_1056.lean",
  "proof_region_guard_status": "passed",
  "proof_use_provenance_status": "passed",
  "proof_use_status": "final_theorem",
  "protected_statement_hash_source": "source_problem",
  "protected_theorem_hash_unchanged": true,
  "report_id": "FinalVerifyGateFull2D:4b337b1a591388dc8286fb8867f6891cdca095691b7a641c64dd2d1d92dcc8be",
  "schema_version": "1.0.0",
  "solver_backed_proof_status": "passed",
  "sorry_status": "clean",
  "target_obligation_id": "full2d-obligation:full2d-curated-1056",
  "theorem_statement_hash": "sha256:84a22994a975dbff5e97203f743bf1b08e894c93c2e729d05b339c7523054b55"
}
