{
  "checked_candidate_file_ref": "sha256:d520aa287e31867c2278b0e6a504ef0b430ecaee788475a70f7117920934ef31",
  "forbidden_axiom_status": "clean",
  "lean_artifact_ref": "C:\\Users\\bakat\\work\\AI_math_research\\runs\\geometry_full2d_v0_4_2\\proof_artifact_batch\\full2d-positive-1507\\worker\\full2d_release_proof_artifact_batch\\full2d-positive-1507\\full2d_synth_1507.lean",
  "lean_status": "passed",
  "proof_artifact_ref": "C:\\Users\\bakat\\work\\AI_math_research\\runs\\geometry_full2d_v0_4_2\\proof_artifact_batch\\full2d-positive-1507\\worker\\full2d_release_proof_artifact_batch\\full2d-positive-1507\\full2d_synth_1507.lean",
  "proof_region_guard_status": "passed",
  "proof_use_provenance_status": "passed",
  "proof_use_status": "final_theorem",
  "protected_statement_hash_source": "source_problem",
  "protected_theorem_hash_unchanged": true,
  "report_id": "FinalVerifyGateFull2D:f74a713ec9985f4b04bad7eb300a55adaad883bc2eabac863f4abc32638df628",
  "schema_version": "1.0.0",
  "solver_backed_proof_status": "passed",
  "sorry_status": "clean",
  "target_obligation_id": "full2d-obligation:full2d-positive-1507",
  "theorem_statement_hash": "sha256:19490923506ab72a96e98161963e757d9d5d5832a429c9681677a21de638bcaf"
}
