{
  "checked_candidate_file_ref": "sha256:ee0940d9fa4a9a189bfb721b511ea36c47e07848371819fe42fe22de9c9ff6cf",
  "forbidden_axiom_status": "clean",
  "lean_artifact_ref": "C:\\Users\\bakat\\work\\AI_math_research\\runs\\geometry_full2d_v0_4_2\\proof_artifact_batch\\full2d-curated-0639\\worker\\full2d_release_proof_artifact_batch\\full2d-curated-0639\\full2d_curated_0639.lean",
  "lean_status": "passed",
  "proof_artifact_ref": "C:\\Users\\bakat\\work\\AI_math_research\\runs\\geometry_full2d_v0_4_2\\proof_artifact_batch\\full2d-curated-0639\\worker\\full2d_release_proof_artifact_batch\\full2d-curated-0639\\full2d_curated_0639.lean",
  "proof_region_guard_status": "passed",
  "proof_use_provenance_status": "passed",
  "proof_use_status": "final_theorem",
  "protected_statement_hash_source": "source_problem",
  "protected_theorem_hash_unchanged": true,
  "report_id": "FinalVerifyGateFull2D:9a7178818fef4e0047c3676a307bc3f59f635641f0797e2ec8c74a4de2d7d1fe",
  "schema_version": "1.0.0",
  "solver_backed_proof_status": "passed",
  "sorry_status": "clean",
  "target_obligation_id": "full2d-obligation:full2d-curated-0639",
  "theorem_statement_hash": "sha256:7e80754e91a88ba7742ba9a484120dc6a0d88c4f6099b78c7f16c80c3b23caa4"
}
