{
  "checked_candidate_file_ref": "sha256:57daf591f17835c5b97b2e2456bdaaea58f0a54083fe446920ea803ca6622871",
  "forbidden_axiom_status": "clean",
  "lean_artifact_ref": "C:\\Users\\bakat\\work\\AI_math_research\\runs\\geometry_full2d_v0_4_2\\proof_artifact_batch\\full2d-curated-3083\\worker\\full2d_release_proof_artifact_batch\\full2d-curated-3083\\full2d_curated_3083.lean",
  "lean_status": "passed",
  "proof_artifact_ref": "C:\\Users\\bakat\\work\\AI_math_research\\runs\\geometry_full2d_v0_4_2\\proof_artifact_batch\\full2d-curated-3083\\worker\\full2d_release_proof_artifact_batch\\full2d-curated-3083\\full2d_curated_3083.lean",
  "proof_region_guard_status": "passed",
  "proof_use_provenance_status": "passed",
  "proof_use_status": "final_theorem",
  "protected_statement_hash_source": "source_problem",
  "protected_theorem_hash_unchanged": true,
  "report_id": "FinalVerifyGateFull2D:ea786f90bff9d98e98e4915736f3adfd477ee343a6187dcbd2b6897aac830288",
  "schema_version": "1.0.0",
  "solver_backed_proof_status": "passed",
  "sorry_status": "clean",
  "target_obligation_id": "full2d-obligation:full2d-curated-3083",
  "theorem_statement_hash": "sha256:47923a1aa9ea2fb448fc70009f52edf28f79d3e38a8a90f9fb7666b3a2755f96"
}
