{
  "checked_candidate_file_ref": "sha256:632e7eef713263be53fb038a443c01c7842255a9b233f83f85036d656bc5341d",
  "forbidden_axiom_status": "clean",
  "lean_artifact_ref": "C:\\Users\\bakat\\work\\AI_math_research\\runs\\geometry_full2d_v0_4_2\\proof_artifact_batch\\full2d-positive-0181\\worker\\full2d_release_proof_artifact_batch\\full2d-positive-0181\\full2d_synth_0181.lean",
  "lean_status": "passed",
  "proof_artifact_ref": "C:\\Users\\bakat\\work\\AI_math_research\\runs\\geometry_full2d_v0_4_2\\proof_artifact_batch\\full2d-positive-0181\\worker\\full2d_release_proof_artifact_batch\\full2d-positive-0181\\full2d_synth_0181.lean",
  "proof_region_guard_status": "passed",
  "proof_use_provenance_status": "passed",
  "proof_use_status": "final_theorem",
  "protected_statement_hash_source": "source_problem",
  "protected_theorem_hash_unchanged": true,
  "report_id": "FinalVerifyGateFull2D:3c0b8bba0730dee618ce13b86d24c7f6651026b15b8208949316c485e12648fa",
  "schema_version": "1.0.0",
  "solver_backed_proof_status": "passed",
  "sorry_status": "clean",
  "target_obligation_id": "full2d-obligation:full2d-positive-0181",
  "theorem_statement_hash": "sha256:b2201403fda40696b6688c5673221f6c5eb7f38ca1bdb382fa277a75b8826c24"
}
